smmtools/__init__.py
smmtools/demo.py
smmtools/fonts/Roboto-Medium.ttf
smmtools/fonts/Roboto-Regular.ttf
SMM_tools-0.1.dist-info/METADATA
SMM_tools-0.1.dist-info/WHEEL
SMM_tools-0.1.dist-info/top_level.txt
SMM_tools-0.1.dist-info/RECORD
