Metadata-Version: 2.1
Name: SMM-tools
Version: 0.1
Summary: Usifull SMM tools for authors
Home-page: https://github.com/dev-muhammad/smm-tools
Author: dev-muhammad
Author-email: iam.markjobs@gmail.com
License: MIT
Keywords: instagram
Platform: UNKNOWN
Classifier: Development Status :: 3 - Alpha
Classifier: License :: OSI Approved :: MIT License
Classifier: Programming Language :: Python :: 3.8
Classifier: Topic :: Multimedia :: Graphics :: Editors
